rcsb/__init__.py
rcsb/utils/__init__.py
rcsb/utils/validation/ValidationReportAdapter.py
rcsb/utils/validation/ValidationReportProvider.py
rcsb/utils/validation/ValidationReportReader.py
rcsb/utils/validation/ValidationReportSchemaUtils.py
rcsb/utils/validation/__init__.py
rcsb_utils_validation-0.35.dist-info/METADATA
rcsb_utils_validation-0.35.dist-info/WHEEL
rcsb_utils_validation-0.35.dist-info/licenses/LICENSE
rcsb_utils_validation-0.35.dist-info/RECORD
